{
  "type": "GROUP",
"name": "Global Information",
"path": "",
"pathFormatted": "group_missing-name-b06d1",
"stats": {
    "name": "Global Information",
    "numberOfRequests": {
        "total": 2,
        "ok": 0,
        "ko": 2
    },
    "minResponseTime": {
        "total": 32,
        "ok": 0,
        "ko": 32
    },
    "maxResponseTime": {
        "total": 281,
        "ok": 0,
        "ko": 281
    },
    "meanResponseTime": {
        "total": 157,
        "ok": 0,
        "ko": 157
    },
    "standardDeviation": {
        "total": 125,
        "ok": 0,
        "ko": 125
    },
    "percentiles1": {
        "total": 157,
        "ok": 0,
        "ko": 157
    },
    "percentiles2": {
        "total": 219,
        "ok": 0,
        "ko": 219
    },
    "percentiles3": {
        "total": 269,
        "ok": 0,
        "ko": 269
    },
    "percentiles4": {
        "total": 279,
        "ok": 0,
        "ko": 279
    },
    "group1": {
    "name": "t < 800 ms",
    "count": 0,
    "percentage": 0
},
    "group2": {
    "name": "800 ms < t < 1200 ms",
    "count": 0,
    "percentage": 0
},
    "group3": {
    "name": "t > 1200 ms",
    "count": 0,
    "percentage": 0
},
    "group4": {
    "name": "failed",
    "count": 2,
    "percentage": 100
},
    "meanNumberOfRequestsPerSecond": {
        "total": 2.0,
        "ok": 0,
        "ko": 2.0
    }
},
"contents": {
"req_010-getauthtoke-4f476": {
        "type": "REQUEST",
        "name": "010_GetAuthToken",
"path": "010_GetAuthToken",
"pathFormatted": "req_010-getauthtoke-4f476",
"stats": {
    "name": "010_GetAuthToken",
    "numberOfRequests": {
        "total": 1,
        "ok": 0,
        "ko": 1
    },
    "minResponseTime": {
        "total": 281,
        "ok": 0,
        "ko": 281
    },
    "maxResponseTime": {
        "total": 281,
        "ok": 0,
        "ko": 281
    },
    "meanResponseTime": {
        "total": 281,
        "ok": 0,
        "ko": 281
    },
    "standardDeviation": {
        "total": 0,
        "ok": 0,
        "ko": 0
    },
    "percentiles1": {
        "total": 281,
        "ok": 0,
        "ko": 281
    },
    "percentiles2": {
        "total": 281,
        "ok": 0,
        "ko": 281
    },
    "percentiles3": {
        "total": 281,
        "ok": 0,
        "ko": 281
    },
    "percentiles4": {
        "total": 281,
        "ok": 0,
        "ko": 281
    },
    "group1": {
    "name": "t < 800 ms",
    "count": 0,
    "percentage": 0
},
    "group2": {
    "name": "800 ms < t < 1200 ms",
    "count": 0,
    "percentage": 0
},
    "group3": {
    "name": "t > 1200 ms",
    "count": 0,
    "percentage": 0
},
    "group4": {
    "name": "failed",
    "count": 1,
    "percentage": 100
},
    "meanNumberOfRequestsPerSecond": {
        "total": 1.0,
        "ok": 0,
        "ko": 1.0
    }
}
    },"req_020-getservicet-47b78": {
        "type": "REQUEST",
        "name": "020_GetServiceToken",
"path": "020_GetServiceToken",
"pathFormatted": "req_020-getservicet-47b78",
"stats": {
    "name": "020_GetServiceToken",
    "numberOfRequests": {
        "total": 1,
        "ok": 0,
        "ko": 1
    },
    "minResponseTime": {
        "total": 32,
        "ok": 0,
        "ko": 32
    },
    "maxResponseTime": {
        "total": 32,
        "ok": 0,
        "ko": 32
    },
    "meanResponseTime": {
        "total": 32,
        "ok": 0,
        "ko": 32
    },
    "standardDeviation": {
        "total": 0,
        "ok": 0,
        "ko": 0
    },
    "percentiles1": {
        "total": 32,
        "ok": 0,
        "ko": 32
    },
    "percentiles2": {
        "total": 32,
        "ok": 0,
        "ko": 32
    },
    "percentiles3": {
        "total": 32,
        "ok": 0,
        "ko": 32
    },
    "percentiles4": {
        "total": 32,
        "ok": 0,
        "ko": 32
    },
    "group1": {
    "name": "t < 800 ms",
    "count": 0,
    "percentage": 0
},
    "group2": {
    "name": "800 ms < t < 1200 ms",
    "count": 0,
    "percentage": 0
},
    "group3": {
    "name": "t > 1200 ms",
    "count": 0,
    "percentage": 0
},
    "group4": {
    "name": "failed",
    "count": 1,
    "percentage": 100
},
    "meanNumberOfRequestsPerSecond": {
        "total": 1.0,
        "ok": 0,
        "ko": 1.0
    }
}
    }
}

}