{
    "name": "Global Information",
    "numberOfRequests": {
        "total": 13,
        "ok": 11,
        "ko": 2
    },
    "minResponseTime": {
        "total": 76,
        "ok": 76,
        "ko": 1194
    },
    "maxResponseTime": {
        "total": 3770,
        "ok": 3770,
        "ko": 1202
    },
    "meanResponseTime": {
        "total": 1452,
        "ok": 1498,
        "ko": 1198
    },
    "standardDeviation": {
        "total": 1082,
        "ok": 1170,
        "ko": 4
    },
    "percentiles1": {
        "total": 1202,
        "ok": 1304,
        "ko": 1198
    },
    "percentiles2": {
        "total": 1408,
        "ok": 1530,
        "ko": 1200
    },
    "percentiles3": {
        "total": 3758,
        "ok": 3760,
        "ko": 1202
    },
    "percentiles4": {
        "total": 3768,
        "ok": 3768,
        "ko": 1202
    },
    "group1": {
    "name": "t < 800 ms",
    "count": 2,
    "percentage": 15
},
    "group2": {
    "name": "800 ms < t < 1200 ms",
    "count": 3,
    "percentage": 23
},
    "group3": {
    "name": "t > 1200 ms",
    "count": 6,
    "percentage": 46
},
    "group4": {
    "name": "failed",
    "count": 2,
    "percentage": 15
},
    "meanNumberOfRequestsPerSecond": {
        "total": 0.13541666666666666,
        "ok": 0.11458333333333333,
        "ko": 0.020833333333333332
    }
}